GraphePython/__init__.py
GraphePython/utils.py
graphepython-1.4.1.dist-info/licenses/LICENSE
graphepython-1.4.1.dist-info/METADATA
graphepython-1.4.1.dist-info/WHEEL
graphepython-1.4.1.dist-info/top_level.txt
graphepython-1.4.1.dist-info/RECORD
