Metadata-Version: 2.4
Name: GraphePython
Version: 1.4.1
Summary: Implementation of Dijkstra's algorithm with graph visualization.
Home-page: https://github.com/SAMSAM55yt/GraphePython
Author: Saubion Sami
Author-email: sami.saubion@gmail.com
License: MIT
Classifier: Programming Language :: Python :: 3
Classifier: License :: OSI Approved :: MIT License
Classifier: Operating System :: OS Independent
Requires-Python: >=3.7
License-File: LICENSE
Requires-Dist: matplotlib>=3.0
Requires-Dist: networkx>=2.0
Dynamic: author
Dynamic: author-email
Dynamic: classifier
Dynamic: description
Dynamic: description-content-type
Dynamic: home-page
Dynamic: license
Dynamic: license-file
Dynamic: requires-dist
Dynamic: requires-python
Dynamic: summary
